ansible/module_utils/viptela/__init__.py
ansible/module_utils/viptela/viptela.py
ansible/module_utils/viptela/vmanage.py
ansible/modules/viptela/__init__.py
ansible/modules/viptela/vmanage_attachment_export.py
ansible/modules/viptela/vmanage_attachment_import.py
ansible/modules/viptela/vmanage_central_policy.py
ansible/modules/viptela/vmanage_central_policy_facts.py
ansible/modules/viptela/vmanage_certificate.py
ansible/modules/viptela/vmanage_cluster_facts.py
ansible/modules/viptela/vmanage_device.py
ansible/modules/viptela/vmanage_device_action_status.py
ansible/modules/viptela/vmanage_device_attachment.py
ansible/modules/viptela/vmanage_device_bootstrap.py
ansible/modules/viptela/vmanage_device_certificate.py
ansible/modules/viptela/vmanage_device_facts.py
ansible/modules/viptela/vmanage_device_template.py
ansible/modules/viptela/vmanage_device_template_facts.py
ansible/modules/viptela/vmanage_feature_template.py
ansible/modules/viptela/vmanage_feature_template_facts.py
ansible/modules/viptela/vmanage_fileupload.py
ansible/modules/viptela/vmanage_local_policy.py
ansible/modules/viptela/vmanage_local_policy_facts.py
ansible/modules/viptela/vmanage_nping.py
ansible/modules/viptela/vmanage_policy_definition.py
ansible/modules/viptela/vmanage_policy_definition_facts.py
ansible/modules/viptela/vmanage_policy_export.py
ansible/modules/viptela/vmanage_policy_import.py
ansible/modules/viptela/vmanage_policy_list.py
ansible/modules/viptela/vmanage_policy_list_facts.py
ansible/modules/viptela/vmanage_security_policy.py
ansible/modules/viptela/vmanage_settings.py
ansible/modules/viptela/vmanage_software_facts.py
ansible/modules/viptela/vmanage_software_upgrade.py
ansible/modules/viptela/vmanage_software_upload.py
ansible/modules/viptela/vmanage_template_export.py
ansible/modules/viptela/vmanage_template_facts.py
ansible/modules/viptela/vmanage_template_import.py
ansible/modules/viptela/vmanage_virtual_image_upload.py
ansible/plugins/httpapi/vmanage.py
vmanage/__main__.py
viptela-0.3.10.dist-info/LICENSE
viptela-0.3.10.dist-info/METADATA
viptela-0.3.10.dist-info/NOTICE
viptela-0.3.10.dist-info/WHEEL
viptela-0.3.10.dist-info/entry_points.txt
viptela-0.3.10.dist-info/top_level.txt
viptela-0.3.10.dist-info/RECORD
