Metadata-Version: 2.1
Name: viptela
Version: 0.3.10
Summary: Cisco DevNet SD-WAN vManage (Viptela) CLI/SDK
License-File: LICENSE
License-File: NOTICE
Requires-Dist: Click
Requires-Dist: requests
Requires-Dist: dictdiffer
Requires-Dist: PyYAML
